[{"home":"Caala","away":"Petro Atletico","score":"2-1","time":"14:00","timer":"Fin","competition":"ANGOLA: Girabola"},{"home":"Argentino de Quilmes","away":"Deportivo Armenio","score":"1-0","time":"19:00","timer":"Fin","competition":"ARGENTINA: Primera C Metropolitana"},{"home":"Sarmiento Junin","away":"All Boys","score":"0-2","time":"20:10","timer":"Fin","competition":"ARGENTINA: Copa Argentina"},{"home":"Hamilton Olympic","away":"Lambton J.","score":"1-1","time":"08:45","timer":"Fin","competition":"AUSTRALIA: Northern NSW"},{"home":"Wilstermann","away":"Always Ready","score":"2-0","time":"22:15","timer":"Fin","competition":"BOLIVIA: Division Profesional - Apertura"},{"home":"CRB","away":"Jacyoba","score":"2-0","time":"23:30","timer":"Fin","competition":"BRAZIL: Campeonato Alagoano - Play Offs"},{"home":"Sao Luiz","away":"EC Sao Jose","score":"2-1","time":"22:15","timer":"Fin","competition":"BRAZIL: Campeonato Gaucho - Play Offs"},{"home":"Crac Go","away":"Vila Nova FC","score":"1-0","time":"23:30","timer":"Fin","competition":"BRAZIL: Campeonato Goiano - Play Offs"},{"home":"Goianesia","away":"Goiania","score":"2-3","time":"23:30","timer":"Fin","competition":"BRAZIL: Campeonato Goiano - Play Offs"},{"home":"Sao Francisco","away":"SAO Raimundo PA","score":"2-2","time":"19:00","timer":"Fin","competition":"BRAZIL: Campeonato Paraense"},{"home":"Cajazeirense de Desportos","away":"Sousa","score":"1-0","time":"23:30","timer":"Fin","competition":"BRAZIL: Campeonato Paraibano"},{"home":"Campinense","away":"Treze PB","score":"0-1","time":"23:30","timer":"Fin","competition":"BRAZIL: Campeonato Paraibano"},{"home":"CSP","away":"Botafogo PB","score":"0-2","time":"23:30","timer":"Fin","competition":"BRAZIL: Campeonato Paraibano"},{"home":"EC de Patos","away":"Nacional de Patos","score":"1-3","time":"23:30","timer":"Fin","competition":"BRAZIL: Campeonato Paraibano"},{"home":"Perilima","away":"Serrano PB","score":"3-3","time":"23:30","timer":"Fin","competition":"BRAZIL: Campeonato Paraibano"},{"home":"Oeste","away":"Botafogo SP","score":"4-3(3-3)","time":"19:30","timer":"Pen","competition":"BRAZIL: Campeonato Paulista - Troféu Interior - Play Offs"},{"home":"Ponte Preta","away":"Bragantino","score":"1-1","time":"22:15","timer":"Fin","competition":"BRAZIL: Campeonato Paulista - Troféu Interior - Play Offs"},{"home":"Palmeiras","away":"Novorizontino","score":"5-0","time":"00:00","timer":"Fin","competition":"BRAZIL: Campeonato Paulista - Play Offs"},{"home":"Ituano","away":"Sao Paulo","score":"0-1","time":"22:15","timer":"Fin","competition":"BRAZIL: Campeonato Paulista - Play Offs"},{"home":"Santa Cruz","away":"Afogados da Ingazeira","score":"1-2(1-1)","time":"22:15","timer":"Pen","competition":"BRAZIL: Campeonato Pernambucano - Play Offs"},{"home":"Julho Esporte","away":"Flamengo PI","score":"2-1","time":"23:00","timer":"Fin","competition":"BRAZIL: Campeonato Piauiense"},{"home":"Parnahyba","away":"AE Altos","score":"2-0","time":"23:00","timer":"Fin","competition":"BRAZIL: Campeonato Piauiense"},{"home":"River-PI","away":"Piaui","score":"0-0","time":"23:00","timer":"Fin","competition":"BRAZIL: Campeonato Piauiense"},{"home":"ABC","away":"Potiguar","score":"1-2","time":"23:30","timer":"Fin","competition":"BRAZIL: Campeonato Potiguar - Second stage"},{"home":"Sergipe","away":"Lagarto","score":"0-0","time":"23:30","timer":"Fin","competition":"BRAZIL: Campeonato Sergipano - Second stage"},{"home":"Chapecoense-SC","away":"Criciuma","score":"3-2","time":"22:15","timer":"Fin","competition":"BRAZIL: Copa do Brasil"},{"home":"Coritiba U20","away":"Palmeiras U20","score":"1-3","time":"18:00","timer":"Fin","competition":"BRAZIL: Copa do Brasil U20"},{"home":"Tubarao U20","away":"Vasco U20","score":"1-2","time":"23:00","timer":"Fin","competition":"BRAZIL: Copa do Brasil U20"},{"home":"Osasco Audax W","away":"Ferroviaria W","score":"0-0","time":"18:00","timer":"Fin","competition":"BRAZIL: Brasileiro Women"},{"home":"Santos W","away":"Sao Francisco W","score":"8-0","time":"18:00","timer":"Fin","competition":"BRAZIL: Brasileiro Women"},{"home":"SAO Jose W","away":"Flamengo W","score":"0-2","time":"22:00","timer":"Fin","competition":"BRAZIL: Brasileiro Women"},{"home":"Young Sports","away":"Eding Sport","score":"0-0","time":"13:00","timer":"Fin","competition":"CAMEROON: Elite One"},{"home":"APEJES Academy","away":"Avion Academy","score":"-","time":"14:30","timer":"Postp","competition":"CAMEROON: Elite One"},{"home":"Bamenda","away":"Union Douala","score":"-","time":"14:30","timer":"Postp","competition":"CAMEROON: Elite One"},{"home":"Eding Sport","away":"Les Astres","score":"-","time":"14:30","timer":"Postp","competition":"CAMEROON: Elite One"},{"home":"Feutcheu","away":"Fortuna Mfou","score":"-","time":"14:30","timer":"Postp","competition":"CAMEROON: Elite One"},{"home":"Fovu Baham","away":"Bafang","score":"-","time":"14:30","timer":"Postp","competition":"CAMEROON: Elite One"},{"home":"New Star","away":"Dragon de Yaounde","score":"-","time":"14:30","timer":"Postp","competition":"CAMEROON: Elite One"},{"home":"Stade Renard","away":"UMS de Loum","score":"-","time":"14:30","timer":"Postp","competition":"CAMEROON: Elite One"},{"home":"Tonnerre","away":"Cotonsport","score":"-","time":"14:30","timer":"Postp","competition":"CAMEROON: Elite One"},{"home":"Palestino","away":"A. Italiano","score":"1-2","time":"20:30","timer":"Fin","competition":"CHILE: Primera Division"},{"home":"Dalian Chanjoy","away":"Jilin Baijia","score":"4-0","time":"07:30","timer":"Fin","competition":"CHINA: Yi League"},{"home":"Junior","away":"U. Magdalena","score":"1-1","time":"23:15","timer":"Fin","competition":"COLOMBIA: Liga Aguila - Apertura"},{"home":"Guadalupe","away":"Carmelita","score":"1-1","time":"21:05","timer":"Fin","competition":"COSTA RICA: Primera Division - Clausura"},{"home":"Groupe Bazano","away":"AS Maniema","score":"0-1","time":"14:30","timer":"Fin","competition":"DR CONGO: Super Ligue"},{"home":"Motema Pembe","away":"Dragons","score":"2-0","time":"14:30","timer":"Fin","competition":"DR CONGO: Super Ligue"},{"home":"Muungano","away":"AS Vita Club","score":"0-3","time":"14:30","timer":"Awarded","competition":"DR CONGO: Super Ligue"},{"home":"Harrogate","away":"Salford","score":"0-1","time":"19:45","timer":"Fin","competition":"ENGLAND: National League"},{"home":"Darlington","away":"Chester","score":"0-1","time":"19:45","timer":"Fin","competition":"ENGLAND: National League North"},{"home":"Tallinna Kalev U21","away":"Flora U21","score":"0-3","time":"17:00","timer":"Fin","competition":"ESTONIA: Esiliiga"},{"home":"Denmark U17","away":"England U17","score":"2-3","time":"13:00","timer":"Fin","competition":"EUROPE: Euro U17 - Qualification - Second stage"},{"home":"Switzerland U17","away":"Croatia U17","score":"1-1","time":"13:00","timer":"Fin","competition":"EUROPE: Euro U17 - Qualification - Second stage"},{"home":"Wolfsburg W","away":"Lyon W","score":"2-4","time":"17:15","timer":"Fin","competition":"EUROPE: Champions League Women"},{"home":"LSK Kvinner W","away":"Barcelona W","score":"0-1","time":"17:30","timer":"Fin","competition":"EUROPE: Champions League Women"},{"home":"Paris SG W","away":"Chelsea W","score":"2-1","time":"18:00","timer":"Fin","competition":"EUROPE: Champions League Women"},{"home":"Bayern Munich W","away":"Slavia Prague W","score":"5-1","time":"18:30","timer":"Fin","competition":"EUROPE: Champions League Women"},{"home":"Belgium U17 W","away":"Finland U17 W","score":"1-0","time":"14:00","timer":"Fin","competition":"EUROPE: Euro U17 Women - Qualification - Second stage"},{"home":"Georgia U17 W","away":"Hungary U17 W","score":"0-4","time":"14:00","timer":"Fin","competition":"EUROPE: Euro U17 Women - Qualification - Second stage"},{"home":"Greece U17 W","away":"England U17 W","score":"0-2","time":"14:00","timer":"Fin","competition":"EUROPE: Euro U17 Women - Qualification - Second stage"},{"home":"Italy U17 W","away":"Denmark U17 W","score":"0-5","time":"14:00","timer":"Fin","competition":"EUROPE: Euro U17 Women - Qualification - Second stage"},{"home":"Slovenia U17 W","away":"Iceland U17 W","score":"1-0","time":"14:00","timer":"Fin","competition":"EUROPE: Euro U17 Women - Qualification - Second stage"},{"home":"Austria U17 W","away":"Wales U17 W","score":"3-0","time":"17:00","timer":"Fin","competition":"EUROPE: Euro U17 Women - Qualification - Second stage"},{"home":"Nordhausen","away":"Viktoria Berlin","score":"4-1","time":"18:00","timer":"Fin","competition":"GERMANY: Regionalliga Nordost"},{"home":"TV Herkenrath","away":"Straelen","score":"1-0","time":"18:30","timer":"Fin","competition":"GERMANY: Regionalliga West"},{"home":"Ingolstadt II","away":"SpVgg Bayreuth","score":"1-4","time":"18:30","timer":"Fin","competition":"GERMANY: Regionalliga Bayern"},{"home":"Ennepetal","away":"Westfalia Rhynern","score":"0-3","time":"18:30","timer":"Fin","competition":"GERMANY: Oberliga Westfalen"},{"home":"FC Gutersloh","away":"Sprockhovel","score":"5-5","time":"18:30","timer":"Fin","competition":"GERMANY: Oberliga Westfalen"},{"home":"Hammer SpVgg.","away":"Ahlen","score":"0-1","time":"18:30","timer":"Fin","competition":"GERMANY: Oberliga Westfalen"},{"home":"Holzwickeder SC","away":"Erndtebruck","score":"4-3","time":"18:30","timer":"Fin","competition":"GERMANY: Oberliga Westfalen"},{"home":"Schermbeck","away":"Gievenbeck","score":"2-1","time":"18:30","timer":"Fin","competition":"GERMANY: Oberliga Westfalen"},{"home":"Siegen","away":"Brunninghausen","score":"1-1","time":"18:30","timer":"Fin","competition":"GERMANY: Oberliga Westfalen"},{"home":"Idar-Oberstein","away":"Schott Mainz","score":"0-5","time":"19:00","timer":"Fin","competition":"GERMANY: Oberliga Rheinland-Pfalz/Saar"},{"home":"B. Monchengladbach W","away":"Duisburg W","score":"0-1","time":"18:00","timer":"Fin","competition":"GERMANY: Bundesliga Women"},{"home":"Volos NFC","away":"Irodotos","score":"5-0","time":"12:00","timer":"Fin","competition":"GREECE: Football League"},{"home":"AO Trikala","away":"Kerkyra","score":"1-0","time":"13:00","timer":"Fin","competition":"GREECE: Football League"},{"home":"Apollon Larissa","away":"Apollon Pontou","score":"3-1","time":"13:00","timer":"Fin","competition":"GREECE: Football League"},{"home":"Ergotelis","away":"Aiginiakos","score":"4-1","time":"13:00","timer":"Fin","competition":"GREECE: Football League"},{"home":"Panachaiki","away":"Chania Kissamikos","score":"1-3","time":"13:00","timer":"Fin","competition":"GREECE: Football League"},{"home":"Platanias FC","away":"Sparti","score":"7-0","time":"13:00","timer":"Fin","competition":"GREECE: Football League"},{"home":"Siquinala","away":"Xelaju","score":"2-1","time":"18:00","timer":"Fin","competition":"GUATEMALA: Liga Nacional - Clausura"},{"home":"Guastatoya","away":"Petapa","score":"6-0","time":"21:00","timer":"Fin","competition":"GUATEMALA: Liga Nacional - Clausura"},{"home":"Monza","away":"L.R. Vicenza","score":"1-1","time":"19:30","timer":"Fin","competition":"ITALY: Coppa Italia Serie C - Play Offs"},{"home":"Viterbese","away":"Trapani","score":"1-0","time":"19:30","timer":"Fin","competition":"ITALY: Coppa Italia Serie C - Play Offs"},{"home":"AC Milan W","away":"AS Roma W","score":"4-1","time":"14:00","timer":"Fin","competition":"ITALY: Serie A Women"},{"home":"Sassuolo W","away":"Juventus W","score":"2-1","time":"14:00","timer":"Fin","competition":"ITALY: Serie A Women"},{"home":"Tavagnacco W","away":"ASD Verona W","score":"1-0","time":"14:00","timer":"Fin","competition":"ITALY: Serie A Women"},{"home":"Aksu","away":"FK Kyran","score":"3-1","time":"09:00","timer":"Fin","competition":"KAZAKHSTAN: Kazakhstan Cup - Qualification"},{"home":"Maqtaaral","away":"FK Akzhayik","score":"2-1","time":"10:00","timer":"Fin","competition":"KAZAKHSTAN: Kazakhstan Cup - Qualification"},{"home":"Sofapaka","away":"Mount Kenya United","score":"3-1","time":"11:00","timer":"Fin","competition":"KENYA: Premier League"},{"home":"Bandari","away":"Kakamega Homeboyz","score":"1-2","time":"12:00","timer":"Fin","competition":"KENYA: Premier League"},{"home":"Tusker","away":"Kariobangi Sharks","score":"3-1","time":"12:00","timer":"Fin","competition":"KENYA: Premier League"},{"home":"Ulinzi Stars","away":"Sony Sugar","score":"2-1","time":"12:00","timer":"Fin","competition":"KENYA: Premier League"},{"home":"Vihiga United","away":"Leopards","score":"2-2","time":"12:00","timer":"Fin","competition":"KENYA: Premier League"},{"home":"Zoo","away":"Gor Mahia","score":"0-4","time":"12:00","timer":"Fin","competition":"KENYA: Premier League"},{"home":"Kenya CB","away":"Western Stima","score":"1-1","time":"13:15","timer":"Fin","competition":"KENYA: Premier League"},{"home":"Prishtina","away":"Flamurtari","score":"3-0","time":"13:00","timer":"Fin","competition":"KOSOVO: Superliga"},{"home":"Olympique Khouribga","away":"Youssoufia Berrechid","score":"1-1","time":"15:00","timer":"Fin","competition":"MOROCCO: Botola Pro"},{"home":"Hassania Agadir","away":"Kawkab Marrakech","score":"5-1","time":"19:00","timer":"Fin","competition":"MOROCCO: Botola Pro"},{"home":"Kano Pillars","away":"Ifeanyi Ubah","score":"3-0","time":"15:00","timer":"Fin","competition":"NIGERIA: NPFL"},{"home":"Lobi Stars","away":"Niger Tornadoes","score":"2-2","time":"15:00","timer":"Fin","competition":"NIGERIA: NPFL"},{"home":"Remo Stars","away":"Enugu Rangers","score":"0-0","time":"15:00","timer":"Fin","competition":"NIGERIA: NPFL"},{"home":"Deportivo Universitario","away":"Costa del Este","score":"0-4","time":"20:30","timer":"Fin","competition":"PANAMA: LPF - Clausura"},{"home":"Nacional Asuncion","away":"Libertad Asuncion","score":"0-1","time":"23:15","timer":"Fin","competition":"PARAGUAY: Primera Division - Apertura"},{"home":"R. Rzeszow","away":"Pogon Siedlce","score":"1-3","time":"14:00","timer":"Fin","competition":"POLAND: Division 2"},{"home":"Arka Gdynia U18","away":"Legia U18","score":"2-0","time":"12:00","timer":"Fin","competition":"POLAND: Central Youth League"},{"home":"Estoril U23","away":"Braga U23","score":"1-1","time":"15:00","timer":"Fin","competition":"PORTUGAL: Liga Revelacao U23 - Championship Group"},{"home":"Fairplay Bucuresti W","away":"Vasas Odorhei W","score":"0-8","time":"10:00","timer":"Fin","competition":"ROMANIA: Romanian Cup Women"},{"home":"Baia Mare W","away":"Ol. Cluj W","score":"1-2","time":"13:00","timer":"Fin","competition":"ROMANIA: Romanian Cup Women"},{"home":"Krasnodar 3","away":"Volgar-Astrakhan","score":"1-1","time":"13:00","timer":"Fin","competition":"RUSSIA: PFL - South"},{"home":"Al-Kawkab","away":"Al-Nahda","score":"1-2","time":"12:45","timer":"Fin","competition":"SAUDI ARABIA: Division 1"},{"home":"Al-Shoalah","away":"Al Adalh","score":"2-0","time":"12:45","timer":"Fin","competition":"SAUDI ARABIA: Division 1"},{"home":"Abha","away":"Al Orubah","score":"1-1","time":"13:00","timer":"Fin","competition":"SAUDI ARABIA: Division 1"},{"home":"Al Taee","away":"Jeddah","score":"2-1","time":"13:10","timer":"Fin","competition":"SAUDI ARABIA: Division 1"},{"home":"Al Khaleej","away":"Al-Qaisumah","score":"3-2","time":"15:35","timer":"Fin","competition":"SAUDI ARABIA: Division 1"},{"home":"Hajer","away":"Al Najoom","score":"2-1","time":"15:35","timer":"Fin","competition":"SAUDI ARABIA: Division 1"},{"home":"St Johnstone","away":"St. Mirren","score":"1-0","time":"19:45","timer":"Fin","competition":"SCOTLAND: Premiership"},{"home":"Cape Umoya United","away":"TS Galaxy","score":"1-2","time":"17:30","timer":"Fin","competition":"SOUTH AFRICA: Nedbank Cup"},{"home":"Argentina U17","away":"Paraguay U17","score":"2-2","time":"00:30","timer":"Fin","competition":"SOUTH AMERICA: South American Championship U17"},{"home":"Chile U17","away":"Venezuela U17","score":"3-0","time":"22:10","timer":"Fin","competition":"SOUTH AMERICA: South American Championship U17"},{"home":"Gimpo C.","away":"Yonsei","score":"4-0","time":"05:00","timer":"Fin","competition":"SOUTH KOREA: Korean Cup"},{"home":"Hwaseong","away":"Ansan Greeners","score":"3-2","time":"05:00","timer":"Fin","competition":"SOUTH KOREA: Korean Cup"},{"home":"Paju Citizen","away":"Ajou","score":"4-0","time":"05:00","timer":"Fin","competition":"SOUTH KOREA: Korean Cup"},{"home":"Pocheon","away":"Gimhae","score":"3-2(2-2)","time":"05:00","timer":"Pen","competition":"SOUTH KOREA: Korean Cup"},{"home":"Yeungnam University","away":"Soongsil","score":"2-1(1-1)","time":"05:00","timer":"Pen","competition":"SOUTH KOREA: Korean Cup"},{"home":"Anyang","away":"Icheon","score":"5-1","time":"06:00","timer":"Fin","competition":"SOUTH KOREA: Korean Cup"},{"home":"Busan","away":"Cheonan City","score":"0-1","time":"06:00","timer":"Fin","competition":"SOUTH KOREA: Korean Cup"},{"home":"Changwon","away":"Hanyang University","score":"3-0","time":"06:00","timer":"Fin","competition":"SOUTH KOREA: Korean Cup"},{"home":"Chuncheon","away":"Honam","score":"0-1","time":"06:00","timer":"Fin","competition":"SOUTH KOREA: Korean Cup"},{"home":"Mokpo City","away":"Jeonju Citizen","score":"1-0","time":"06:00","timer":"Fin","competition":"SOUTH KOREA: Korean Cup"},{"home":"Asan Mugunghwa","away":"Yangpyeong","score":"0-1(0-0)","time":"10:00","timer":"Pen","competition":"SOUTH KOREA: Korean Cup"},{"home":"Busan Kyotong","away":"Gyeongju KHNP","score":"2-3(1-1)","time":"10:00","timer":"AET","competition":"SOUTH KOREA: Korean Cup"},{"home":"Cheongju","away":"Incheon University","score":"1-0","time":"10:00","timer":"Fin","competition":"SOUTH KOREA: Korean Cup"},{"home":"Daejeon","away":"Dankook University","score":"2-3(2-2)","time":"10:00","timer":"Pen","competition":"SOUTH KOREA: Korean Cup"},{"home":"Daejeon Korail","away":"Jeonju","score":"2-1(0-0)","time":"10:00","timer":"AET","competition":"SOUTH KOREA: Korean Cup"},{"home":"Gyeongju Citizen","away":"Gangneung","score":"0-1(0-0)","time":"10:00","timer":"AET","competition":"SOUTH KOREA: Korean Cup"},{"home":"Jeonnam","away":"Gwangju FC","score":"0-1","time":"10:00","timer":"Fin","competition":"SOUTH KOREA: Korean Cup"},{"home":"Suwon City","away":"Chungju Citizen","score":"6-0","time":"10:00","timer":"Fin","competition":"SOUTH KOREA: Korean Cup"},{"home":"Bucheon FC 1995","away":"Seoul E.","score":"1-3(1-1)","time":"10:30","timer":"AET","competition":"SOUTH KOREA: Korean Cup"},{"home":"Baden","away":"Kosova","score":"4-0","time":"19:00","timer":"Fin","competition":"SWITZERLAND: 1.Liga Classic Group 3"},{"home":"Ahal","away":"FC Asgabat","score":"2-0","time":"14:00","timer":"Fin","competition":"TURKMENISTAN: Yokary Liga"},{"home":"Vipers","away":"Maroons","score":"2-0","time":"13:00","timer":"Fin","competition":"UGANDA: Premier League"},{"home":"Jinja","away":"Kampala City","score":"0-2","time":"13:30","timer":"Fin","competition":"UGANDA: Premier League"},{"home":"Onduparaka FC","away":"Villa","score":"2-1","time":"13:30","timer":"Fin","competition":"UGANDA: Premier League"},{"home":"Inhulets","away":"Rukh Vynnyky","score":"0-0","time":"12:00","timer":"Fin","competition":"UKRAINE: Persha Liga"},{"home":"Balkany","away":"Hirnyk-Sport","score":"2-0","time":"13:00","timer":"Fin","competition":"UKRAINE: Persha Liga"},{"home":"Kramatorsk","away":"Kolos Kovalyovka","score":"0-1","time":"15:00","timer":"Fin","competition":"UKRAINE: Persha Liga"},{"home":"Prykarpattya","away":"Mykolaiv","score":"1-2","time":"16:00","timer":"Fin","competition":"UKRAINE: Persha Liga"},{"home":"Obolon Brovar Kyjev","away":"Metalist 1925","score":"1-0","time":"17:00","timer":"Fin","competition":"UKRAINE: Persha Liga"},{"home":"Monagas","away":"Trujillanos","score":"2-1","time":"19:30","timer":"Fin","competition":"VENEZUELA: Primera Division - Apertura"},{"home":"Zamora","away":"Llaneros","score":"3-0","time":"20:00","timer":"Fin","competition":"VENEZUELA: Primera Division - Apertura"},{"home":"Honduras","away":"Ecuador","score":"0-0","time":"00:00","timer":"Fin","competition":"WORLD: Friendly International"},{"home":"Peru","away":"El Salvador","score":"0-2","time":"00:00","timer":"Fin","competition":"WORLD: Friendly International"},{"home":"Nicaragua","away":"Guatemala","score":"0-1","time":"01:30","timer":"Fin","competition":"WORLD: Friendly International"},{"home":"Costa Rica","away":"Jamaica","score":"1-0","time":"02:00","timer":"Fin","competition":"WORLD: Friendly International"},{"home":"Mexico","away":"Paraguay","score":"4-2","time":"02:00","timer":"Fin","competition":"WORLD: Friendly International"},{"home":"Myanmar U19","away":"Thailand U19","score":"0-1","time":"08:00","timer":"Fin","competition":"WORLD: Friendly International"},{"home":"Belarus U19","away":"Lithuania U19","score":"2-0","time":"09:00","timer":"Fin","competition":"WORLD: Friendly International"},{"home":"Vietnam U19","away":"China U19","score":"1-0","time":"10:30","timer":"Fin","competition":"WORLD: Friendly International"},{"home":"Luxembourg U18","away":"Belgium U18","score":"1-1","time":"16:00","timer":"Fin","competition":"WORLD: Friendly International"},{"home":"Shakhtar Donetsk (Ukr)","away":"Olimpik Donetsk (Ukr)","score":"4-0","time":"09:00","timer":"Fin","competition":"WORLD: Club Friendly"},{"home":"Konyaspor (Tur)","away":"Adana Demirspor (Tur)","score":"2-1","time":"11:00","timer":"Fin","competition":"WORLD: Club Friendly"},{"home":"FK Zorya Luhansk (Ukr)","away":"Mariupol (Ukr)","score":"2-2","time":"13:00","timer":"Fin","competition":"WORLD: Club Friendly"},{"home":"Oleksandriya (Ukr)","away":"Kremin (Ukr)","score":"3-1","time":"13:00","timer":"Fin","competition":"WORLD: Club Friendly"},{"home":"KuPS (Fin)","away":"AC Kajaani (Fin)","score":"0-1","time":"13:30","timer":"Fin","competition":"WORLD: Club Friendly"},{"home":"Zenit Petersburg 2 (Rus)","away":"HJK (Fin)","score":"0-1","time":"13:45","timer":"Fin","competition":"WORLD: Club Friendly"},{"home":"Denizlispor (Tur)","away":"Goztepe (Tur)","score":"1-0","time":"16:00","timer":"Fin","competition":"WORLD: Club Friendly"},{"home":"GBK Kokkola (Fin)","away":"KPV Kokkola (Fin)","score":"2-0","time":"16:30","timer":"Fin","competition":"WORLD: Club Friendly"},{"home":"Bologna U19","away":"Genoa U19","score":"2-1(1-1)","time":"14:00","timer":"Pen","competition":"WORLD: Viareggio Cup - Play Offs"}]
