[{"home":"Mlila","away":"Paradou","score":"1-0","time":"15:00","timer":"Fin","competition":"ALGERIA: Ligue 1"},{"home":"Bel Abbes","away":"MC Alger","score":"2-1","time":"21:30","timer":"Fin","competition":"ALGERIA: Ligue 1"},{"home":"Bordj Bou Arreridj","away":"Medea","score":"1-0","time":"21:30","timer":"Fin","competition":"ALGERIA: Ligue 1"},{"home":"Hussein Dey","away":"JS Kabylie","score":"1-2","time":"21:30","timer":"Fin","competition":"ALGERIA: Ligue 1"},{"home":"MO Bejaia","away":"CR Belouizdad","score":"1-0","time":"21:30","timer":"Fin","competition":"ALGERIA: Ligue 1"},{"home":"Saoura","away":"ES Setif","score":"2-1","time":"21:30","timer":"Fin","competition":"ALGERIA: Ligue 1"},{"home":"Tadjenant","away":"Constantine","score":"0-0","time":"21:30","timer":"Fin","competition":"ALGERIA: Ligue 1"},{"home":"USM Alger","away":"Oran","score":"1-1","time":"21:30","timer":"Fin","competition":"ALGERIA: Ligue 1"},{"home":"Central Cordoba","away":"Almagro","score":"2-1","time":"00:10","timer":"Fin","competition":"ARGENTINA: Primera B Nacional - Promotion - Play Offs"},{"home":"Jeonbuk (Kor)","away":"Buriram (Tha)","score":"0-0","time":"10:00","timer":"Fin","competition":"ASIA: AFC Champions League"},{"home":"Shanghai SIPG (Chn)","away":"Ulsan Hyundai (Kor)","score":"5-0","time":"10:00","timer":"Fin","competition":"ASIA: AFC Champions League"},{"home":"Sydney FC (Aus)","away":"Kawasaki Frontale (Jpn)","score":"0-4","time":"10:00","timer":"Fin","competition":"ASIA: AFC Champions League"},{"home":"Urawa (Jpn)","away":"Beijing Guoan (Chn)","score":"3-0","time":"10:00","timer":"Fin","competition":"ASIA: AFC Champions League"},{"home":"Lok. Tashkent (Uzb)","away":"Al Rayyan (Qat)","score":"3-2","time":"14:00","timer":"Fin","competition":"ASIA: AFC Champions League"},{"home":"Al Wasl (Uae)","away":"Al Zawraa (Irq)","score":"1-5","time":"18:00","timer":"Fin","competition":"ASIA: AFC Champions League"},{"home":"Zob Ahan (Irn)","away":"Al-Nassr (Sau)","score":"-","time":"18:00","timer":"Postp","competition":"ASIA: AFC Champions League"},{"home":"Al-Ittihad FC (Sau)","away":"Al Wahda (Uae)","score":"1-1","time":"19:00","timer":"Fin","competition":"ASIA: AFC Champions League"},{"home":"BJMC","away":"Abahani Chittagong","score":"1-1","time":"10:00","timer":"Fin","competition":"BANGLADESH: Premier League"},{"home":"Guabira","away":"San Jose","score":"2-1","time":"19:30","timer":"Fin","competition":"BOLIVIA: Division Profesional - Apertura"},{"home":"Criciuma","away":"Guarani","score":"1-0","time":"22:15","timer":"Fin","competition":"BRAZIL: Serie B"},{"home":"Botev Plovdiv","away":"Ludogorets","score":"0-2","time":"15:00","timer":"Fin","competition":"BULGARIA: Parva Liga - Championship Group"},{"home":"Levski Sofia","away":"CSKA Sofia","score":"0-2","time":"15:00","timer":"Fin","competition":"BULGARIA: Parva Liga - Championship Group"},{"home":"Cherno More","away":"Beroe","score":"0-0","time":"18:00","timer":"Fin","competition":"BULGARIA: Parva Liga - Championship Group"},{"home":"Chico","away":"Quindio","score":"1-0","time":"01:00","timer":"Fin","competition":"COLOMBIA: Torneo Aguila - Apertura - Quadrangular"},{"home":"Skovshoved","away":"BK Frem","score":"1-2","time":"17:00","timer":"Fin","competition":"DENMARK: 2nd Division - Relegation Group"},{"home":"Guayaquil City","away":"Aucas","score":"1-1","time":"00:15","timer":"Fin","competition":"ECUADOR: Liga Pro"},{"home":"El Gaish","away":"Al Ittihad","score":"4-0","time":"20:00","timer":"Fin","competition":"EGYPT: Premier League"},{"home":"El Masry","away":"El-Entag El-Harby","score":"2-2","time":"20:00","timer":"Fin","competition":"EGYPT: Premier League"},{"home":"Enppi","away":"Misr Elmaqasah","score":"2-1","time":"20:00","timer":"Fin","competition":"EGYPT: Premier League"},{"home":"Smouha","away":"Petrojet","score":"2-0","time":"20:00","timer":"Fin","competition":"EGYPT: Premier League"},{"home":"Wadi Degla","away":"Haras El Hodood","score":"1-1","time":"20:00","timer":"Fin","competition":"EGYPT: Premier League"},{"home":"Levadia","away":"Kalju","score":"0-0","time":"16:30","timer":"Fin","competition":"ESTONIA: Meistriliiga"},{"home":"Lahden Reipas","away":"MiPK","score":"2-1","time":"15:30","timer":"Fin","competition":"FINLAND: Kakkonen Group A"},{"home":"Paris FC","away":"Lens","score":"1-2(1-1)","time":"18:45","timer":"Pen","competition":"FRANCE: Ligue 1 - Relegation"},{"home":"Bali United","away":"Bhayangkara Utd","score":"1-0","time":"13:30","timer":"Fin","competition":"INDONESIA: Liga 1"},{"home":"Persebaya","away":"Kalteng Putra","score":"1-1","time":"13:30","timer":"Fin","competition":"INDONESIA: Liga 1"},{"home":"Al Najaf","away":"Al Kahraba","score":"1-1","time":"19:00","timer":"Fin","competition":"IRAQ: Super League"},{"home":"Naft Al Junoob","away":"Al Karkh","score":"0-0","time":"19:00","timer":"Fin","competition":"IRAQ: Super League"},{"home":"St. Patricks","away":"Derry City","score":"1-0","time":"18:45","timer":"Fin","competition":"IRELAND: Premier Division"},{"home":"Cittadella","away":"Benevento","score":"1-2","time":"19:00","timer":"Fin","competition":"ITALY: Serie B - Play Offs"},{"home":"Jelgava","away":"Spartaks","score":"0-3","time":"15:30","timer":"Fin","competition":"LATVIA: Optibet Virsliga"},{"home":"Metta/LU","away":"FK Liepaja","score":"1-2","time":"15:30","timer":"Fin","competition":"LATVIA: Optibet Virsliga"},{"home":"Atlantas","away":"Palanga","score":"2-1","time":"15:00","timer":"Fin","competition":"LITHUANIA: A Lyga"},{"home":"Riteriai","away":"FK Panevezys","score":"1-1","time":"17:00","timer":"Fin","competition":"LITHUANIA: A Lyga"},{"home":"Utrecht","away":"Heracles","score":"3-0","time":"16:30","timer":"Fin","competition":"NETHERLANDS: Eredivisie - Europa League - Play Offs"},{"home":"Vitesse","away":"Groningen","score":"3-1","time":"18:45","timer":"Fin","competition":"NETHERLANDS: Eredivisie - Europa League - Play Offs"},{"home":"Elverum","away":"Stabaek","score":"1-6","time":"16:00","timer":"Fin","competition":"NORWAY: NM Cup"},{"home":"FC Hermannstadt","away":"FC Botosani","score":"0-2","time":"15:30","timer":"Fin","competition":"ROMANIA: Liga 1 - Relegation Group"},{"home":"U. Cluj","away":"Sportul Snagov","score":"1-0","time":"17:30","timer":"Fin","competition":"ROMANIA: Liga 2"},{"home":"River Plate (Uru)","away":"Colon Santa FE (Arg)","score":"0-0","time":"22:15","timer":"Fin","competition":"SOUTH AMERICA: Copa Sudamericana"},{"home":"Royal Pari (Bol)","away":"Macara (Ecu)","score":"1-0","time":"22:15","timer":"Fin","competition":"SOUTH AMERICA: Copa Sudamericana"},{"home":"U. Catolica (Ecu)","away":"FBC Melgar (Per)","score":"6-0","time":"22:15","timer":"Fin","competition":"SOUTH AMERICA: Copa Sudamericana"},{"home":"Degerfors","away":"Dalkurd","score":"1-2","time":"17:00","timer":"Fin","competition":"SWEDEN: Superettan"},{"home":"GAIS","away":"Vasteras SK","score":"1-1","time":"17:00","timer":"Fin","competition":"SWEDEN: Superettan"},{"home":"Bromolla","away":"Lunds","score":"0-4","time":"17:00","timer":"Fin","competition":"SWEDEN: Svenska Cupen - Qualification"},{"home":"IK Franke","away":"Upsala","score":"0-2","time":"17:00","timer":"Fin","competition":"SWEDEN: Svenska Cupen - Qualification"},{"home":"Vargarda IK","away":"Lindome","score":"2-1(1-1)","time":"17:00","timer":"Pen","competition":"SWEDEN: Svenska Cupen - Qualification"},{"home":"St. Gallen II","away":"Linth","score":"3-1","time":"17:30","timer":"Fin","competition":"SWITZERLAND: 1.Liga Classic Group 3"},{"home":"Mbao","away":"Kinondoni MC","score":"0-2","time":"13:00","timer":"Fin","competition":"TANZANIA: Ligi Kuu Bara"},{"home":"Singida United","away":"Simba","score":"0-2","time":"13:00","timer":"Fin","competition":"TANZANIA: Ligi Kuu Bara"},{"home":"Karagumruk","away":"Manisa","score":"2-0","time":"13:00","timer":"Fin","competition":"TURKEY: 2. Lig Play Offs"},{"home":"Sariyer","away":"Sakaryaspor","score":"0-0","time":"13:00","timer":"Fin","competition":"TURKEY: 2. Lig Play Offs"},{"home":"Ch. Odessa","away":"Karpaty","score":"3-1","time":"14:00","timer":"Fin","competition":"UKRAINE: Premier League - Relegation Group"},{"home":"Desna","away":"Vorskla Poltava","score":"0-1","time":"14:00","timer":"Fin","competition":"UKRAINE: Premier League - Relegation Group"},{"home":"Arsenal Kiev","away":"Olimpik Donetsk","score":"1-1","time":"16:30","timer":"Fin","competition":"UKRAINE: Premier League - Relegation Group"},{"home":"Shakhtar Donetsk U21","away":"Dynamo Kiev U21","score":"1-1","time":"10:00","timer":"Fin","competition":"UKRAINE: Youth League - Winners stage"},{"home":"Vorskla Poltava U21","away":"Oleksandriya U21","score":"2-0","time":"10:00","timer":"Fin","competition":"UKRAINE: Youth League - Winners stage"},{"home":"Arsenal Kiev U21","away":"Zorya U21","score":"3-4","time":"12:00","timer":"Fin","competition":"UKRAINE: Youth League - Winners stage"},{"home":"Desna U21","away":"Olimpik Donetsk U21","score":"-","time":"09:00","timer":"Awarded","competition":"UKRAINE: Youth League - Losers stage"},{"home":"Mariupol U21","away":"Lviv U21","score":"3-0","time":"09:00","timer":"Fin","competition":"UKRAINE: Youth League - Losers stage"},{"home":"Houston FC","away":"Corpus Christi FC","score":"1-5","time":"00:00","timer":"Fin","competition":"USA: USL League Two"},{"home":"Tormenta II","away":"Discoveries","score":"4-0","time":"00:00","timer":"Fin","competition":"USA: USL League Two"},{"home":"Flint City","away":"Chicago United","score":"1-0","time":"15:00","timer":"Fin","competition":"USA: USL League Two"},{"home":"Beitar Jerusalem (Isr)","away":"Atl. Madrid (Esp)","score":"2-1","time":"16:30","timer":"Fin","competition":"WORLD: Club Friendly"},{"home":"Croatia U18","away":"Czech Republic U18","score":"1-1","time":"10:00","timer":"Fin","competition":"WORLD: Slovakia Cup"},{"home":"Ukraine U18","away":"Spain U18","score":"1-2","time":"10:00","timer":"Fin","competition":"WORLD: Slovakia Cup"},{"home":"Russia U18","away":"Mexico U18","score":"2-0","time":"15:00","timer":"Fin","competition":"WORLD: Slovakia Cup"},{"home":"Slovakia U18","away":"England U18","score":"2-2","time":"16:00","timer":"Fin","competition":"WORLD: Slovakia Cup"}]
