[{"home":"San Martin T.","away":"Agropecuario","score":"3-2(2-2)","time":"00:35","timer":"Pen","competition":"ARGENTINA: Copa Argentina"},{"home":"Almagro","away":"Atl. Rafaela","score":"2-1(1-1)","time":"20:10","timer":"Pen","competition":"ARGENTINA: Copa Argentina"},{"home":"Velez Sarsfield","away":"Real Pilar","score":"0-1","time":"23:10","timer":"Fin","competition":"ARGENTINA: Copa Argentina"},{"home":"Hobart Zebras","away":"Clarence Utd.","score":"9-0","time":"08:00","timer":"Fin","competition":"AUSTRALIA: NPL Tasmania"},{"home":"Charlestown City Blues","away":"Newcastle Jets U21","score":"1-3","time":"08:45","timer":"Fin","competition":"AUSTRALIA: Northern NSW"},{"home":"Malkia","away":"Al-Hidd","score":"0-2","time":"14:25","timer":"Fin","competition":"BAHRAIN: Premier League"},{"home":"Al-Najma","away":"Al-Muharraq","score":"0-0","time":"15:30","timer":"Fin","competition":"BAHRAIN: Premier League"},{"home":"Al-Hala","away":"East Riffa","score":"2-0","time":"17:00","timer":"Fin","competition":"BAHRAIN: Premier League"},{"home":"The Strongest","away":"Guabira","score":"5-0","time":"00:30","timer":"Fin","competition":"BOLIVIA: Division Profesional - Apertura"},{"home":"Estrela do Norte","away":"Itapemirim","score":"1-2","time":"23:15","timer":"Fin","competition":"BRAZIL: Campeonato Capixaba"},{"home":"Marcilio Dias","away":"Figueirense","score":"0-0","time":"00:30","timer":"Fin","competition":"BRAZIL: Campeonato Catarinense"},{"home":"Guarany","away":"Barbalha","score":"4-1","time":"00:30","timer":"Fin","competition":"BRAZIL: Campeonato Cearense - Second stage"},{"home":"Tapajos","away":"Remo","score":"0-0","time":"23:00","timer":"Fin","competition":"BRAZIL: Campeonato Paraense"},{"home":"Salgueiro","away":"Santa Cruz","score":"2-0","time":"00:30","timer":"Fin","competition":"BRAZIL: Campeonato Pernambucano - First stage"},{"home":"Fluminense","away":"Ypiranga FC","score":"3-0","time":"00:30","timer":"Fin","competition":"BRAZIL: Copa do Brasil"},{"home":"Mixto","away":"Chapecoense-SC","score":"1-2","time":"00:30","timer":"Fin","competition":"BRAZIL: Copa do Brasil"},{"home":"Avai","away":"Brasil de Pelotas","score":"2-0","time":"22:15","timer":"Fin","competition":"BRAZIL: Copa do Brasil"},{"home":"ABC","away":"Moto Club","score":"3-2(2-2)","time":"23:30","timer":"Pen","competition":"BRAZIL: Copa do Brasil"},{"home":"Nautico","away":"Sampaio Correa","score":"2-1","time":"22:00","timer":"Fin","competition":"BRAZIL: Copa do Nordeste"},{"home":"Fortaleza","away":"Confianca","score":"4-0","time":"23:30","timer":"Fin","competition":"BRAZIL: Copa do Nordeste"},{"home":"El-Entag El-Harby","away":"Al Ittihad","score":"2-4","time":"17:00","timer":"Fin","competition":"EGYPT: Premier League"},{"home":"Charlton U23","away":"Colchester U23","score":"3-1","time":"13:00","timer":"Fin","competition":"ENGLAND: Professional Development League"},{"home":"Tallinna Kalev U21","away":"Tammeka U21","score":"2-1","time":"17:00","timer":"Fin","competition":"ESTONIA: Esiliiga"},{"home":"Tartu Welco","away":"Elva","score":"2-2","time":"17:00","timer":"Fin","competition":"ESTONIA: Esiliiga"},{"home":"D. Zagreb","away":"Benfica","score":"1-0","time":"17:55","timer":"Fin","competition":"EUROPE: Europa League - Play Offs"},{"home":"Eintracht Frankfurt","away":"Inter","score":"0-0","time":"17:55","timer":"Fin","competition":"EUROPE: Europa League - Play Offs"},{"home":"Rennes","away":"Arsenal","score":"3-1","time":"17:55","timer":"Fin","competition":"EUROPE: Europa League - Play Offs"},{"home":"Sevilla","away":"Slavia Prague","score":"2-2","time":"17:55","timer":"Fin","competition":"EUROPE: Europa League - Play Offs"},{"home":"Zenit Petersburg","away":"Villarreal","score":"1-3","time":"17:55","timer":"Fin","competition":"EUROPE: Europa League - Play Offs"},{"home":"Chelsea","away":"Dyn. Kyiv","score":"3-0","time":"20:00","timer":"Fin","competition":"EUROPE: Europa League - Play Offs"},{"home":"Napoli","away":"Salzburg","score":"3-0","time":"20:00","timer":"Fin","competition":"EUROPE: Europa League - Play Offs"},{"home":"Valencia","away":"Krasnodar","score":"2-1","time":"20:00","timer":"Fin","competition":"EUROPE: Europa League - Play Offs"},{"home":"Quevilly Rouen","away":"Le Mans","score":"1-1","time":"19:30","timer":"Fin","competition":"FRANCE: National"},{"home":"Glacis United","away":"Europa FC","score":"1-6","time":"19:30","timer":"Fin","competition":"GIBRALTAR: Premier Division"},{"home":"Chania Kissamikos","away":"Platanias FC","score":"2-2","time":"15:00","timer":"Fin","competition":"GREECE: Football League"},{"home":"UPNFM","away":"Marathon","score":"0-0","time":"00:00","timer":"Fin","competition":"HONDURAS: Liga Nacional - Clausura"},{"home":"Olimpia","away":"Vida","score":"4-0","time":"01:00","timer":"Fin","competition":"HONDURAS: Liga Nacional - Clausura"},{"home":"Real Espana","away":"Juticalpa","score":"0-0","time":"01:00","timer":"Fin","competition":"HONDURAS: Liga Nacional - Clausura"},{"home":"Fylkir","away":"Njardvik","score":"3-1","time":"19:00","timer":"Fin","competition":"ICELAND: League Cup"},{"home":"Haukar","away":"Hafnarfjordur","score":"1-3","time":"19:00","timer":"Fin","competition":"ICELAND: League Cup"},{"home":"Valur","away":"Fram","score":"2-1","time":"19:00","timer":"Fin","competition":"ICELAND: League Cup"},{"home":"North East Utd","away":"Bengaluru","score":"2-1","time":"14:00","timer":"Fin","competition":"INDIA: ISL - Play Offs"},{"home":"Persebaya","away":"Persib Bandung","score":"3-2","time":"08:30","timer":"Fin","competition":"INDONESIA: President Cup"},{"home":"TIRA Persikabo","away":"Perseru Serui","score":"3-2","time":"11:30","timer":"Fin","competition":"INDONESIA: President Cup"},{"home":"Machine Sazi","away":"Tractor","score":"0-2","time":"11:30","timer":"Fin","competition":"IRAN: Persian Gulf Pro League"},{"home":"Esteghlal Khuzestan","away":"Paykan","score":"0-1","time":"12:00","timer":"Fin","competition":"IRAN: Persian Gulf Pro League"},{"home":"Saipa","away":"Foolad","score":"1-0","time":"12:30","timer":"Fin","competition":"IRAN: Persian Gulf Pro League"},{"home":"Padideh Khorasan","away":"Zob Ahan","score":"0-1","time":"13:30","timer":"Fin","competition":"IRAN: Persian Gulf Pro League"},{"home":"Benevento U19","away":"Ascoli U19","score":"1-1","time":"13:30","timer":"Fin","competition":"ITALY: Primavera 2"},{"home":"Al Hussein","away":"Aqaba","score":"1-1","time":"14:00","timer":"Fin","competition":"JORDAN: Premier League"},{"home":"Al-Faisaly Amman","away":"Al Wehdat","score":"2-1","time":"16:30","timer":"Fin","competition":"JORDAN: Premier League"},{"home":"Al Ghazieh","away":"Al Ahed","score":"0-1","time":"12:15","timer":"Fin","competition":"LEBANON: Premier League"},{"home":"Zacatepec","away":"Juarez","score":"2-1","time":"01:00","timer":"Fin","competition":"MEXICO: Liga de Ascenso - Clausura"},{"home":"Cimarrones de Sonora","away":"Celaya","score":"0-2","time":"03:00","timer":"Fin","competition":"MEXICO: Liga de Ascenso - Clausura"},{"home":"Leones Negros","away":"Dorados de Sinaloa","score":"0-0","time":"03:00","timer":"Fin","competition":"MEXICO: Liga de Ascenso - Clausura"},{"home":"Independiente","away":"Sporting Kansas City","score":"2-1","time":"01:00","timer":"Fin","competition":"NORTH & CENTRAL AMERICA: CONCACAF Champions League"},{"home":"Monterrey","away":"Atlanta United","score":"3-0","time":"03:00","timer":"Fin","competition":"NORTH & CENTRAL AMERICA: CONCACAF Champions League"},{"home":"Al Nasr","away":"Al Suwaiq","score":"1-1","time":"11:50","timer":"Fin","competition":"OMAN: Professional League"},{"home":"Shamal","away":"Al Wakra","score":"1-1","time":"15:00","timer":"Fin","competition":"QATAR: Division 2"},{"home":"Ural","away":"Spartak Moscow","score":"1-0","time":"14:00","timer":"Fin","competition":"RUSSIA: Russian Cup"},{"home":"Al-Shabab","away":"Al-Faisaly","score":"2-1","time":"15:40","timer":"Fin","competition":"SAUDI ARABIA: Saudi Professional League"},{"home":"Al-Taawon","away":"Al-Raed","score":"2-1","time":"17:30","timer":"Fin","competition":"SAUDI ARABIA: Saudi Professional League"},{"home":"Alianza Lima (Per)","away":"River Plate (Arg)","score":"1-1","time":"00:30","timer":"Fin","competition":"SOUTH AMERICA: Copa Libertadores"},{"home":"Junior (Col)","away":"Palmeiras (Bra)","score":"0-2","time":"00:30","timer":"Fin","competition":"SOUTH AMERICA: Copa Libertadores"},{"home":"Rosario Central (Arg)","away":"Gremio (Bra)","score":"1-1","time":"00:30","timer":"Fin","competition":"SOUTH AMERICA: Copa Libertadores"},{"home":"Zamora (Ven)","away":"Nacional (Uru)","score":"0-1","time":"00:30","timer":"Fin","competition":"SOUTH AMERICA: Copa Libertadores"},{"home":"Huracan (Arg)","away":"Cruzeiro (Bra)","score":"0-1","time":"22:00","timer":"Fin","competition":"SOUTH AMERICA: Copa Libertadores"},{"home":"CDFC Calzada","away":"Vianes","score":"5-0","time":"19:00","timer":"Fin","competition":"SPAIN: Tercera Division - Group 16"},{"home":"Etoile Sahel","away":"Hammam-Lif","score":"2-1","time":"13:30","timer":"Fin","competition":"TUNISIA: Ligue Professionnelle 1"},{"home":"Sfaxien","away":"Metlaoui","score":"2-0","time":"13:30","timer":"Fin","competition":"TUNISIA: Ligue Professionnelle 1"},{"home":"Song Lam Nghe An","away":"Binh Duong","score":"2-1","time":"09:30","timer":"Fin","competition":"VIETNAM: V.League 1"},{"home":"Da Nang","away":"BHTS Quang Nam","score":"2-2","time":"10:00","timer":"Fin","competition":"VIETNAM: V.League 1"},{"home":"El Salvador","away":"Guatemala","score":"3-1","time":"03:30","timer":"Fin","competition":"WORLD: Friendly International"},{"home":"Cyprus U19","away":"Greece U19","score":"1-1","time":"09:00","timer":"Fin","competition":"WORLD: Friendly International"},{"home":"Austria U17","away":"Georgia U17","score":"1-1","time":"10:00","timer":"Fin","competition":"WORLD: Friendly International"},{"home":"Serbia U17","away":"Bosnia & Herzegovina U17","score":"2-2","time":"10:00","timer":"Fin","competition":"WORLD: Friendly International"},{"home":"Northern Ireland U18","away":"Scotland U18","score":"1-0","time":"15:00","timer":"Fin","competition":"WORLD: Friendly International"},{"home":"Neman (Blr)","away":"Lida (Blr)","score":"0-0","time":"10:00","timer":"Fin","competition":"WORLD: Club Friendly"},{"home":"Torpedo Minsk (Blr)","away":"Energetik-BGU (Blr)","score":"0-0","time":"11:00","timer":"Fin","competition":"WORLD: Club Friendly"},{"home":"Ham-Kam (Nor)","away":"Notodden (Nor)","score":"2-2","time":"12:00","timer":"Fin","competition":"WORLD: Club Friendly"},{"home":"Strommen (Nor)","away":"Tromsdalen (Nor)","score":"1-0","time":"15:30","timer":"Fin","competition":"WORLD: Club Friendly"},{"home":"Levanger (Nor)","away":"Stjordals Blink (Nor)","score":"2-2","time":"17:30","timer":"Fin","competition":"WORLD: Club Friendly"},{"home":"Nardo (Nor)","away":"Byasen (Nor)","score":"1-2","time":"18:30","timer":"Fin","competition":"WORLD: Club Friendly"},{"home":"Slovenia U17 W","away":"Hungary U17 W","score":"0-4","time":"11:00","timer":"Fin","competition":"WORLD: Friendly International Women"}]
