[{"home":"Kamza","away":"Skenderbeu","score":"-","time":"15:00","timer":"Postp","competition":"ALBANIA: Albanian Cup"},{"home":"KF Tirana","away":"Laci","score":"3-0","time":"16:00","timer":"Fin","competition":"ALBANIA: Albanian Cup"},{"home":"Magra","away":"Bejaia","score":"2-1","time":"14:00","timer":"Fin","competition":"ALGERIA: Ligue 2"},{"home":"C.R.D. Libolo","away":"Caala","score":"2-0","time":"14:00","timer":"Fin","competition":"ANGOLA: Girabola"},{"home":"Cubango","away":"Saurimo","score":"3-1","time":"14:00","timer":"Fin","competition":"ANGOLA: Girabola"},{"home":"Desportivo Huila","away":"Interclube","score":"1-0","time":"14:00","timer":"Fin","competition":"ANGOLA: Girabola"},{"home":"Lobito","away":"Onze Bravos","score":"0-0","time":"14:00","timer":"Fin","competition":"ANGOLA: Girabola"},{"home":"Progresso","away":"Sagrada","score":"0-1","time":"14:00","timer":"Fin","competition":"ANGOLA: Girabola"},{"home":"Santa Rita","away":"Primeiro de Agosto","score":"0-1","time":"14:00","timer":"Fin","competition":"ANGOLA: Girabola"},{"home":"Petro Atletico","away":"Sporting de Cabinda","score":"1-0","time":"16:30","timer":"Fin","competition":"ANGOLA: Girabola"},{"home":"Ind. Rivadavia","away":"Sarmiento Junin","score":"0-0","time":"00:40","timer":"Fin","competition":"ARGENTINA: Primera B Nacional"},{"home":"Acassuso","away":"Flandria","score":"2-2","time":"19:00","timer":"Fin","competition":"ARGENTINA: Primera B Metropolitana"},{"home":"Defensores Unidos","away":"San Miguel","score":"1-2","time":"19:00","timer":"Fin","competition":"ARGENTINA: Primera B Metropolitana"},{"home":"Justo Jose de Urquiza","away":"Almirante Brown","score":"1-0","time":"19:00","timer":"Fin","competition":"ARGENTINA: Primera B Metropolitana"},{"home":"Tristan Suarez","away":"San Telmo","score":"0-1","time":"19:00","timer":"Fin","competition":"ARGENTINA: Primera B Metropolitana"},{"home":"Talleres (R.E)","away":"All Boys","score":"2-0","time":"23:00","timer":"Fin","competition":"ARGENTINA: Primera B Metropolitana"},{"home":"Patronato","away":"Dock Sud","score":"2-1(1-1)","time":"20:10","timer":"Pen","competition":"ARGENTINA: Copa Argentina"},{"home":"Kawasaki Frontale (Jpn)","away":"Sydney FC (Aus)","score":"1-0","time":"10:00","timer":"Fin","competition":"ASIA: AFC Champions League"},{"home":"Ulsan Hyundai (Kor)","away":"Shanghai SIPG (Chn)","score":"1-0","time":"10:00","timer":"Fin","competition":"ASIA: AFC Champions League"},{"home":"Buriram (Tha)","away":"Jeonbuk (Kor)","score":"1-0","time":"11:00","timer":"Fin","competition":"ASIA: AFC Champions League"},{"home":"Beijing Guoan (Chn)","away":"Urawa (Jpn)","score":"0-0","time":"12:00","timer":"Fin","competition":"ASIA: AFC Champions League"},{"home":"Khujand (Taj)","away":"Ahal (Tkm)","score":"0-0","time":"09:00","timer":"Fin","competition":"ASIA: AFC Cup - Qualification - Play Offs"},{"home":"Tai Po (Hkg)","away":"Ryomyong (Prk)","score":"1-0(0-0)","time":"12:00","timer":"Pen","competition":"ASIA: AFC Cup - Qualification - Play Offs"},{"home":"Chennaiyin (Ind)","away":"Colombo (Sri)","score":"1-0","time":"14:00","timer":"Fin","competition":"ASIA: AFC Cup - Qualification - Play Offs"},{"home":"Kaya (Phl)","away":"Home Utd (Sin)","score":"5-0","time":"07:00","timer":"Fin","competition":"ASIA: AFC Cup"},{"home":"PSM Makassar (Ina)","away":"Lao Toyota (Lao)","score":"7-3","time":"08:00","timer":"Fin","competition":"ASIA: AFC Cup"},{"home":"India W","away":"Maldives W","score":"6-0","time":"09:15","timer":"Fin","competition":"ASIA: SAFF Championship Women"},{"home":"Launceston","away":"Devonport","score":"1-2","time":"07:30","timer":"Fin","competition":"AUSTRALIA: NPL Tasmania"},{"home":"Kingborough Lions","away":"Clarence Utd.","score":"8-0","time":"09:00","timer":"Fin","competition":"AUSTRALIA: NPL Tasmania"},{"home":"Glenorchy Knights","away":"Olympia Warriors","score":"1-3","time":"09:15","timer":"Fin","competition":"AUSTRALIA: NPL Tasmania"},{"home":"Real Potosi","away":"Aurora","score":"2-2","time":"22:15","timer":"Fin","competition":"BOLIVIA: Division Profesional - Apertura"},{"home":"Klis Buturovic Polje","away":"Sloga Crnjelovo","score":"2-2","time":"14:00","timer":"Fin","competition":"BOSNIA AND HERZEGOVINA: Bosnia and Herzegovina Cup"},{"home":"TOSK Tesanj","away":"Gradacac","score":"4-1","time":"14:00","timer":"Fin","competition":"BOSNIA AND HERZEGOVINA: Bosnia and Herzegovina Cup"},{"home":"Zrinjski","away":"FK Sarajevo","score":"0-1","time":"15:00","timer":"Fin","competition":"BOSNIA AND HERZEGOVINA: Bosnia and Herzegovina Cup"},{"home":"Borac Banja Luka","away":"Siroki Brijeg","score":"0-1","time":"17:00","timer":"Fin","competition":"BOSNIA AND HERZEGOVINA: Bosnia and Herzegovina Cup"},{"home":"Tupy","away":"Rio Branco-VN","score":"1-1","time":"18:00","timer":"Fin","competition":"BRAZIL: Campeonato Capixaba"},{"home":"Vitoria ES","away":"Real Noroeste","score":"3-2","time":"18:00","timer":"Fin","competition":"BRAZIL: Campeonato Capixaba"},{"home":"Rio Branco ES","away":"Castelo","score":"6-1","time":"23:15","timer":"Fin","competition":"BRAZIL: Campeonato Capixaba"},{"home":"Serra","away":"Estrela do Norte","score":"1-1","time":"23:15","timer":"Fin","competition":"BRAZIL: Campeonato Capixaba"},{"home":"Serrano PB","away":"EC de Patos","score":"2-2","time":"23:30","timer":"Fin","competition":"BRAZIL: Campeonato Paraibano"},{"home":"Sport Recife","away":"Salgueiro","score":"4-0","time":"22:15","timer":"Fin","competition":"BRAZIL: Campeonato Pernambucano - First stage"},{"home":"Afogados da Ingazeira","away":"Flamengo Arcoverde","score":"2-1","time":"23:00","timer":"Fin","competition":"BRAZIL: Campeonato Pernambucano - First stage"},{"home":"Petrolina","away":"Academica Vitoria","score":"0-0","time":"23:00","timer":"Fin","competition":"BRAZIL: Campeonato Pernambucano - First stage"},{"home":"AE Altos","away":"Flamengo PI","score":"4-2","time":"18:45","timer":"Fin","competition":"BRAZIL: Campeonato Piauiense"},{"home":"Assu RN","away":"Santa Cruz de Natal","score":"0-3","time":"23:00","timer":"Fin","competition":"BRAZIL: Campeonato Potiguar - Second stage"},{"home":"Globo","away":"America RN","score":"1-0","time":"23:00","timer":"Fin","competition":"BRAZIL: Campeonato Potiguar - Second stage"},{"home":"Palmeira da Una","away":"CE Forca E Luz","score":"0-1","time":"23:00","timer":"Fin","competition":"BRAZIL: Campeonato Potiguar - Second stage"},{"home":"Botafogo PB","away":"Londrina","score":"0-2","time":"22:15","timer":"Fin","competition":"BRAZIL: Copa do Brasil"},{"home":"America RN U20","away":"Porto PE U20","score":"2-1","time":"18:00","timer":"Fin","competition":"BRAZIL: Copa do Brasil U20"},{"home":"Chapecoense-SC U20","away":"Serra U20","score":"4-0","time":"18:00","timer":"Fin","competition":"BRAZIL: Copa do Brasil U20"},{"home":"Corinthians U20","away":"River AC U20","score":"5-1","time":"18:00","timer":"Fin","competition":"BRAZIL: Copa do Brasil U20"},{"home":"Coritiba U20","away":"Sete de Dourados U20","score":"5-1","time":"18:00","timer":"Fin","competition":"BRAZIL: Copa do Brasil U20"},{"home":"Capital U20","away":"Gremio U20","score":"0-5","time":"22:30","timer":"Fin","competition":"BRAZIL: Copa do Brasil U20"},{"home":"Bahia","away":"Sergipe","score":"0-1","time":"22:30","timer":"Fin","competition":"BRAZIL: Copa do Nordeste"},{"home":"Popayan","away":"Atletico F.C.","score":"2-2","time":"19:00","timer":"Fin","competition":"COLOMBIA: Copa Aguila"},{"home":"Tigres","away":"Llaneros","score":"0-0","time":"19:00","timer":"Fin","competition":"COLOMBIA: Copa Aguila"},{"home":"Dep. Pasto","away":"America De Cali","score":"0-2","time":"20:00","timer":"Fin","competition":"COLOMBIA: Copa Aguila"},{"home":"Fortaleza","away":"Millonarios","score":"0-1","time":"20:00","timer":"Fin","competition":"COLOMBIA: Copa Aguila"},{"home":"Leones","away":"Envigado","score":"0-0","time":"20:00","timer":"Fin","competition":"COLOMBIA: Copa Aguila"},{"home":"Orsomarso","away":"Huila","score":"3-0","time":"20:00","timer":"Fin","competition":"COLOMBIA: Copa Aguila"},{"home":"Real San Andres","away":"Cartagena","score":"1-0","time":"20:30","timer":"Fin","competition":"COLOMBIA: Copa Aguila"},{"home":"U. Magdalena","away":"Barranquilla","score":"1-0","time":"20:30","timer":"Fin","competition":"COLOMBIA: Copa Aguila"},{"home":"Kolding IF","away":"Midtjylland","score":"0-2","time":"17:00","timer":"Fin","competition":"DENMARK: Landspokal Cup"},{"home":"Birmingham","away":"Millwall","score":"0-2","time":"19:45","timer":"Fin","competition":"ENGLAND: Championship"},{"home":"Derby","away":"Stoke","score":"0-0","time":"19:45","timer":"Fin","competition":"ENGLAND: Championship"},{"home":"Middlesbrough","away":"Preston","score":"1-2","time":"19:45","timer":"Fin","competition":"ENGLAND: Championship"},{"home":"Norwich","away":"Hull","score":"3-2","time":"19:45","timer":"Fin","competition":"ENGLAND: Championship"},{"home":"Nottingham","away":"Aston Villa","score":"1-3","time":"19:45","timer":"Fin","competition":"ENGLAND: Championship"},{"home":"QPR","away":"Rotherham","score":"1-2","time":"19:45","timer":"Fin","competition":"ENGLAND: Championship"},{"home":"West Brom","away":"Swansea","score":"3-0","time":"20:00","timer":"Fin","competition":"ENGLAND: Championship"},{"home":"Barnsley U23","away":"Sheffield Wed U23","score":"0-0","time":"13:00","timer":"Fin","competition":"ENGLAND: Professional Development League"},{"home":"Crewe U23","away":"Bristol City U23","score":"3-0","time":"13:00","timer":"Fin","competition":"ENGLAND: Professional Development League"},{"home":"Bolton U23","away":"QPR U23","score":"2-1","time":"19:00","timer":"Fin","competition":"ENGLAND: Professional Development League"},{"home":"Leicester U23","away":"Bayern II","score":"1-2(1-1)","time":"19:00","timer":"Pen","competition":"ENGLAND: Premier League International Cup - Play Offs"},{"home":"Liverpool W","away":"Chelsea W","score":"0-4","time":"19:00","timer":"Fin","competition":"ENGLAND: Women’s Super League"},{"home":"Reading W","away":"Manchester City W","score":"3-4","time":"19:30","timer":"Fin","competition":"ENGLAND: Women’s Super League"},{"home":"West Ham W","away":"Everton W","score":"0-1","time":"19:45","timer":"Fin","competition":"ENGLAND: Women’s Super League"},{"home":"Yeovil W","away":"Brighton W","score":"1-1","time":"19:45","timer":"Fin","competition":"ENGLAND: Women’s Super League"},{"home":"Charlton W","away":"Millwall W","score":"3-0","time":"19:45","timer":"Fin","competition":"ENGLAND: Women’s Championship"},{"home":"Barcelona","away":"Lyon","score":"5-1","time":"20:00","timer":"Fin","competition":"EUROPE: Champions League - Play Offs"},{"home":"Bayern Munich","away":"Liverpool","score":"1-3","time":"20:00","timer":"Fin","competition":"EUROPE: Champions League - Play Offs"},{"home":"FC Porto U19","away":"Tottenham U19","score":"2-0","time":"11:00","timer":"Fin","competition":"EUROPE: UEFA Youth League - Play Offs"},{"home":"Midtjylland U19","away":"Manchester Utd U19","score":"3-1","time":"13:00","timer":"Fin","competition":"EUROPE: UEFA Youth League - Play Offs"},{"home":"Chelsea U19","away":"Montpellier U19","score":"2-1","time":"17:00","timer":"Fin","competition":"EUROPE: UEFA Youth League - Play Offs"},{"home":"Netherlands U17 W","away":"Switzerland U17 W","score":"6-0","time":"11:00","timer":"Fin","competition":"EUROPE: Euro U17 Women - Qualification - Second stage"},{"home":"Serbia U17 W","away":"Russia U17 W","score":"4-1","time":"16:00","timer":"Fin","competition":"EUROPE: Euro U17 Women - Qualification - Second stage"},{"home":"Grossaspach","away":"Wehen","score":"2-3","time":"18:00","timer":"Fin","competition":"GERMANY: 3. Liga"},{"home":"Hallescher","away":"Energie Cottbus","score":"2-3","time":"18:00","timer":"Fin","competition":"GERMANY: 3. Liga"},{"home":"Jena","away":"Lotte","score":"1-1","time":"18:00","timer":"Fin","competition":"GERMANY: 3. Liga"},{"home":"Kaiserslautern","away":"Braunschweig","score":"0-0","time":"18:00","timer":"Fin","competition":"GERMANY: 3. Liga"},{"home":"Karlsruher","away":"Aalen","score":"0-3","time":"18:00","timer":"Fin","competition":"GERMANY: 3. Liga"},{"home":"Oberlausitz","away":"Hertha Berlin II","score":"-","time":"15:00","timer":"Postp","competition":"GERMANY: Regionalliga Nordost"},{"home":"Auerbach","away":"Altglienicke","score":"3-3","time":"18:00","timer":"Fin","competition":"GERMANY: Regionalliga Nordost"},{"home":"Babelsberg","away":"Berliner AK 07","score":"1-1","time":"18:00","timer":"Fin","competition":"GERMANY: Regionalliga Nordost"},{"home":"BFC Dynamo","away":"Chemnitzer","score":"2-1","time":"18:00","timer":"Fin","competition":"GERMANY: Regionalliga Nordost"},{"home":"Meuselwitz","away":"Nordhausen","score":"1-4","time":"18:00","timer":"Fin","competition":"GERMANY: Regionalliga Nordost"},{"home":"Viktoria Berlin","away":"Rathenow","score":"2-0","time":"18:00","timer":"Fin","competition":"GERMANY: Regionalliga Nordost"},{"home":"Hoffenheim II","away":"FC 08 Homburg","score":"0-2","time":"18:00","timer":"Fin","competition":"GERMANY: Regionalliga Sudwest"},{"home":"FSV Frankfurt","away":"Kickers Offenbach","score":"2-0","time":"18:30","timer":"Fin","competition":"GERMANY: Regionalliga Sudwest"},{"home":"Holzwickeder SC","away":"Erndtebruck","score":"-","time":"18:30","timer":"Postp","competition":"GERMANY: Oberliga Westfalen"},{"home":"B. Monchengladbach W","away":"Freiburg W","score":"1-6","time":"15:30","timer":"Fin","competition":"GERMANY: DFB Pokal Women"},{"home":"Wolfsburg W","away":"Potsdam W","score":"4-0","time":"17:00","timer":"Fin","competition":"GERMANY: DFB Pokal Women"},{"home":"Gibraltar Phoenix","away":"Lions Gibraltar","score":"4-0","time":"17:15","timer":"Fin","competition":"GIBRALTAR: Gibraltar Cup"},{"home":"Magpies","away":"Europa FC","score":"1-9","time":"19:30","timer":"Fin","competition":"GIBRALTAR: Gibraltar Cup"},{"home":"Budaorsi SC","away":"Honved","score":"1-2","time":"13:30","timer":"Fin","competition":"HUNGARY: Hungarian Cup"},{"home":"Puskas Academy","away":"Soroksar","score":"1-1","time":"14:00","timer":"Fin","competition":"HUNGARY: Hungarian Cup"},{"home":"Ferencvaros","away":"MOL Vidi","score":"1-2","time":"17:00","timer":"Fin","competition":"HUNGARY: Hungarian Cup"},{"home":"Valur","away":"Afturelding","score":"6-0","time":"18:00","timer":"Fin","competition":"ICELAND: League Cup"},{"home":"Grotta","away":"Hafnarfjordur","score":"1-7","time":"20:00","timer":"Fin","competition":"ICELAND: League Cup"},{"home":"Barito Putera","away":"Persela Lamongan","score":"1-1","time":"08:30","timer":"Fin","competition":"INDONESIA: President Cup"},{"home":"Arema FC","away":"Persita","score":"6-1","time":"11:30","timer":"Fin","competition":"INDONESIA: President Cup"},{"home":"L.R. Vicenza","away":"Monza","score":"0-1","time":"19:30","timer":"Fin","competition":"ITALY: Coppa Italia Serie C - Play Offs"},{"home":"Viterbese","away":"Pisa","score":"3-2","time":"19:30","timer":"Fin","competition":"ITALY: Coppa Italia Serie C - Play Offs"},{"home":"G-Osaka","away":"Yamaga","score":"2-1","time":"10:00","timer":"Fin","competition":"JAPAN: YBC Levain Cup"},{"home":"Kashiwa","away":"Sagan Tosu","score":"0-1","time":"10:00","timer":"Fin","competition":"JAPAN: YBC Levain Cup"},{"home":"Kobe","away":"C-Osaka","score":"0-0","time":"10:00","timer":"Fin","competition":"JAPAN: YBC Levain Cup"},{"home":"Nagoya","away":"Oita","score":"2-1","time":"10:00","timer":"Fin","competition":"JAPAN: YBC Levain Cup"},{"home":"Sapporo","away":"V-Varen Nagasaki","score":"0-0","time":"10:00","timer":"Fin","competition":"JAPAN: YBC Levain Cup"},{"home":"Shimizu","away":"Iwata","score":"1-0","time":"10:00","timer":"Fin","competition":"JAPAN: YBC Levain Cup"},{"home":"Shonan","away":"Yokohama M.","score":"2-0","time":"10:00","timer":"Fin","competition":"JAPAN: YBC Levain Cup"},{"home":"Vegalta Sendai","away":"FC Tokyo","score":"2-1","time":"10:00","timer":"Fin","competition":"JAPAN: YBC Levain Cup"},{"home":"Al Buqaa","away":"Sama Al Sarhan","score":"3-0","time":"14:00","timer":"Fin","competition":"JORDAN: Jordan Cup"},{"home":"Al Yarmouk","away":"Al Hashemeya","score":"4-1","time":"14:00","timer":"Fin","competition":"JORDAN: Jordan Cup"},{"home":"Mansheyat","away":"Jerash","score":"2-1(1-1)","time":"14:00","timer":"Pen","competition":"JORDAN: Jordan Cup"},{"home":"Al Ramtha","away":"Hartha","score":"8-1","time":"16:30","timer":"Fin","competition":"JORDAN: Jordan Cup"},{"home":"Kariobangi Sharks","away":"Nzoia Sugar","score":"1-0","time":"12:00","timer":"Fin","competition":"KENYA: Premier League"},{"home":"Leopards","away":"Sofapaka","score":"0-1","time":"12:00","timer":"Fin","competition":"KENYA: Premier League"},{"home":"Western Stima","away":"Chemelil","score":"0-2","time":"12:00","timer":"Fin","competition":"KENYA: Premier League"},{"home":"Birkirkara","away":"Hamrun","score":"0-1","time":"17:00","timer":"Fin","competition":"MALTA: Premier League"},{"home":"Pieta Hotspurs","away":"Floriana","score":"0-2","time":"17:00","timer":"Fin","competition":"MALTA: Premier League"},{"home":"Balzan","away":"Gzira","score":"0-0","time":"19:00","timer":"Fin","competition":"MALTA: Premier League"},{"home":"Mosta","away":"Valletta","score":"0-1","time":"19:15","timer":"Fin","competition":"MALTA: Premier League"},{"home":"U.N.A.M.- Pumas","away":"Dorados de Sinaloa","score":"3-0","time":"01:00","timer":"Fin","competition":"MEXICO: Copa Mexico - Clausura - Play Offs"},{"home":"Monarcas","away":"Club Tijuana","score":"0-1","time":"03:05","timer":"Fin","competition":"MEXICO: Copa Mexico - Clausura - Play Offs"},{"home":"Titograd","away":"Sutjeska","score":"0-1","time":"12:30","timer":"Fin","competition":"MONTENEGRO: Prva Crnogorska Liga"},{"home":"Buducnost","away":"OFK Petrovac","score":"3-0","time":"14:00","timer":"Fin","competition":"MONTENEGRO: Prva Crnogorska Liga"},{"home":"Iskra","away":"Mornar Bar","score":"1-1","time":"14:00","timer":"Fin","competition":"MONTENEGRO: Prva Crnogorska Liga"},{"home":"Rudar","away":"Lovcen","score":"2-1","time":"14:00","timer":"Fin","competition":"MONTENEGRO: Prva Crnogorska Liga"},{"home":"Zeta","away":"Grbalj","score":"1-0","time":"14:00","timer":"Fin","competition":"MONTENEGRO: Prva Crnogorska Liga"},{"home":"Berkane","away":"Raja Casablanca","score":"3-7","time":"16:00","timer":"Fin","competition":"MOROCCO: Botola Pro"},{"home":"IR Tanger","away":"Hassania Agadir","score":"1-0","time":"18:00","timer":"Fin","competition":"MOROCCO: Botola Pro"},{"home":"Ajax","away":"Zwolle","score":"2-1","time":"17:30","timer":"Fin","competition":"NETHERLANDS: Eredivisie"},{"home":"Diriangen","away":"Ocotal","score":"1-1","time":"21:00","timer":"Fin","competition":"NICARAGUA: Primera Division - Clausura"},{"home":"Ferretti","away":"Real Madriz","score":"0-0","time":"21:00","timer":"Fin","competition":"NICARAGUA: Primera Division - Clausura"},{"home":"Managua FC","away":"Chinandega","score":"3-1","time":"22:00","timer":"Fin","competition":"NICARAGUA: Primera Division - Clausura"},{"home":"Lobi Stars","away":"MFM FC","score":"2-1","time":"15:00","timer":"Fin","competition":"NIGERIA: NPFL"},{"home":"Santos Laguna","away":"New York Red Bulls","score":"4-2","time":"01:00","timer":"Fin","competition":"NORTH & CENTRAL AMERICA: CONCACAF Champions League"},{"home":"U.A.N.L.- Tigres","away":"Houston Dynamo","score":"1-0","time":"03:00","timer":"Fin","competition":"NORTH & CENTRAL AMERICA: CONCACAF Champions League"},{"home":"Mirbat","away":"Majees SC","score":"1-1","time":"13:50","timer":"Fin","competition":"OMAN: Professional League"},{"home":"Dhofar","away":"Sur Club","score":"0-0","time":"15:55","timer":"Fin","competition":"OMAN: Professional League"},{"home":"Plaza Amador","away":"Alianza","score":"1-1","time":"01:00","timer":"Fin","competition":"PANAMA: LPF - Clausura"},{"home":"Rakow","away":"Legia","score":"2-1(1-1)","time":"17:00","timer":"AET","competition":"POLAND: Polish Cup"},{"home":"Al Bidda","away":"Al Wakra","score":"0-4","time":"15:00","timer":"Fin","competition":"QATAR: Division 2"},{"home":"Al Muaidar","away":"Al Mesaimeer","score":"2-1","time":"17:15","timer":"Fin","competition":"QATAR: Division 2"},{"home":"Universitatea Galati W","away":"CSS Targoviste W","score":"4-1","time":"09:00","timer":"Fin","competition":"ROMANIA: Romanian Cup Women"},{"home":"Al-Kawkab","away":"Al Jabalain","score":"1-0","time":"12:50","timer":"Fin","competition":"SAUDI ARABIA: Division 1"},{"home":"Abha","away":"Al Mojzel","score":"2-0","time":"13:05","timer":"Fin","competition":"SAUDI ARABIA: Division 1"},{"home":"Al Orubah","away":"Al Ain","score":"1-1","time":"13:15","timer":"Fin","competition":"SAUDI ARABIA: Division 1"},{"home":"Al Jeel","away":"Al Ansar","score":"0-1","time":"15:30","timer":"Fin","competition":"SAUDI ARABIA: Division 1"},{"home":"Al Khaleej","away":"Al Najoom","score":"0-0","time":"15:30","timer":"Fin","competition":"SAUDI ARABIA: Division 1"},{"home":"Sp. Subotica","away":"Mladost","score":"1-2","time":"13:00","timer":"Fin","competition":"SERBIA: Serbian Cup"},{"home":"Napredak","away":"Partizan","score":"0-4","time":"14:30","timer":"Fin","competition":"SERBIA: Serbian Cup"},{"home":"Radnicki Nis","away":"Vojvodina","score":"2-1","time":"16:00","timer":"Fin","competition":"SERBIA: Serbian Cup"},{"home":"FK Crvena zvezda","away":"Radnik","score":"2-1","time":"17:00","timer":"Fin","competition":"SERBIA: Serbian Cup"},{"home":"FC Kosice","away":"Trnava","score":"0-1(0-0)","time":"14:00","timer":"Pen","competition":"SLOVAKIA: Slovak Cup"},{"home":"Michalovce","away":"Poprad","score":"2-1","time":"16:00","timer":"Fin","competition":"SLOVAKIA: Slovak Cup"},{"home":"Baroka","away":"Golden Arrows","score":"0-1","time":"17:30","timer":"Fin","competition":"SOUTH AFRICA: Premier League"},{"home":"Gremio (Bra)","away":"Libertad Asuncion (Par)","score":"0-1","time":"00:30","timer":"Fin","competition":"SOUTH AMERICA: Copa Libertadores"},{"home":"Nacional (Uru)","away":"Atletico-MG (Bra)","score":"1-0","time":"00:30","timer":"Fin","competition":"SOUTH AMERICA: Copa Libertadores"},{"home":"Sporting Cristal (Per)","away":"Godoy Cruz (Arg)","score":"1-1","time":"00:30","timer":"Fin","competition":"SOUTH AMERICA: Copa Libertadores"},{"home":"Cerro Porteno (Par)","away":"Zamora (Ven)","score":"2-1","time":"22:15","timer":"Fin","competition":"SOUTH AMERICA: Copa Libertadores"},{"home":"San Lorenzo (Arg)","away":"Junior (Col)","score":"1-0","time":"22:15","timer":"Fin","competition":"SOUTH AMERICA: Copa Libertadores"},{"home":"Athletic Bilbao W","away":"EDF Logrono W","score":"4-3","time":"17:00","timer":"Fin","competition":"SPAIN: Primera Division Women"},{"home":"Sevilla FC W","away":"Malaga W","score":"5-0","time":"17:00","timer":"Fin","competition":"SPAIN: Primera Division Women"},{"home":"Madrid C. W","away":"Espanyol W","score":"1-1","time":"19:00","timer":"Fin","competition":"SPAIN: Primera Division Women"},{"home":"Rayo Vallecano W","away":"Atl. Madrid W","score":"0-3","time":"19:30","timer":"Fin","competition":"SPAIN: Primera Division Women"},{"home":"Zurich W","away":"Yverdon W","score":"6-1","time":"19:00","timer":"Fin","competition":"SWITZERLAND: Nationalliga A Women"},{"home":"Esperance Tunis","away":"Sfaxien","score":"2-1","time":"13:30","timer":"Fin","competition":"TUNISIA: Ligue Professionnelle 1"},{"home":"Monastir","away":"Etoile Sahel","score":"3-1","time":"13:30","timer":"Fin","competition":"TUNISIA: Ligue Professionnelle 1"},{"home":"Ahal","away":"FC Asgabat","score":"-","time":"14:00","timer":"Postp","competition":"TURKMENISTAN: Yokary Liga"},{"home":"Police","away":"Paidha Black Angels","score":"4-2","time":"13:00","timer":"Fin","competition":"UGANDA: Premier League"},{"home":"Bright Stars","away":"Nyamityobora","score":"2-1","time":"13:30","timer":"Fin","competition":"UGANDA: Premier League"},{"home":"Mbarara City","away":"Ndejje University","score":"0-0","time":"13:30","timer":"Fin","competition":"UGANDA: Premier League"},{"home":"Sarpsborg 08 (Nor)","away":"Raufoss (Nor)","score":"-","time":"12:00","timer":"Canc","competition":"WORLD: Club Friendly"},{"home":"Sogndal (Nor)","away":"Kristiansund (Nor)","score":"0-0","time":"12:00","timer":"Fin","competition":"WORLD: Club Friendly"},{"home":"Slavia Mozyr (Blr)","away":"Bryne (Nor)","score":"0-0","time":"13:00","timer":"Fin","competition":"WORLD: Club Friendly"},{"home":"Sarpsborg 08 (Nor)","away":"Kongsvinger (Nor)","score":"5-0","time":"13:30","timer":"Fin","competition":"WORLD: Club Friendly"},{"home":"Mjondalen (Nor)","away":"Orgryte (Swe)","score":"-","time":"14:00","timer":"Canc","competition":"WORLD: Club Friendly"},{"home":"Sandnes (Nor)","away":"Egersunds (Nor)","score":"3-0","time":"17:00","timer":"Fin","competition":"WORLD: Club Friendly"},{"home":"Norrby (Swe)","away":"Varbergs (Swe)","score":"2-3","time":"17:30","timer":"Fin","competition":"WORLD: Club Friendly"},{"home":"Bologna U19","away":"Ternana U19","score":"3-2","time":"14:00","timer":"Fin","competition":"WORLD: Viareggio Cup"},{"home":"Braga U19","away":"APIA Tigers U19","score":"4-0","time":"14:00","timer":"Fin","competition":"WORLD: Viareggio Cup"},{"home":"Club Brugge U19","away":"Viareggio U19","score":"8-2","time":"14:00","timer":"Fin","competition":"WORLD: Viareggio Cup"},{"home":"Nania U19","away":"Euro New York U19","score":"2-1","time":"14:00","timer":"Fin","competition":"WORLD: Viareggio Cup"},{"home":"Norchi Tbilisi U19","away":"Athletico-PR U19","score":"1-4","time":"14:00","timer":"Fin","competition":"WORLD: Viareggio Cup"},{"home":"Nordsjaelland U19","away":"UYSS New York U19","score":"1-2","time":"14:00","timer":"Fin","competition":"WORLD: Viareggio Cup"},{"home":"Torino U19","away":"Rieti U19","score":"3-0","time":"14:00","timer":"Fin","competition":"WORLD: Viareggio Cup"},{"home":"Empoli U19","away":"Ascoli U19","score":"0-0","time":"14:45","timer":"Fin","competition":"WORLD: Viareggio Cup"},{"home":"Parma U19","away":"Venezia U19","score":"2-1","time":"16:45","timer":"Fin","competition":"WORLD: Viareggio Cup"},{"home":"Inter U19","away":"Cagliari U19","score":"2-0","time":"18:30","timer":"Fin","competition":"WORLD: Viareggio Cup"}]
